pycouchbase/__init__.py
pycouchbase/connection.py
pycouchbase/document.py
pycouchbase/errors.py
pycouchbase/fields.py
pycouchbase/middlewares.py
pycouchbase/schema.py
pycouchbase/utils.py
pycouchbase/viewsync.py
pycouchbase-0.1.0b1.dist-info/DESCRIPTION.rst
pycouchbase-0.1.0b1.dist-info/METADATA
pycouchbase-0.1.0b1.dist-info/metadata.json
pycouchbase-0.1.0b1.dist-info/pbr.json
pycouchbase-0.1.0b1.dist-info/RECORD
pycouchbase-0.1.0b1.dist-info/top_level.txt
pycouchbase-0.1.0b1.dist-info/WHEEL
