Metadata-Version: 2.0
Name: pycouchbase
Version: 0.1.0b1
Summary: PyCouchbase
Home-page: https://github.com/ardydedase/pycouchbase
Author: Ardy Dedase
Author-email: ardy.dedase@gmail.com
License: BSD
Keywords: pycouchbase database couchbase python nosql couchbasekit sdk
Platform: UNKNOWN
Classifier: Development Status :: 4 - Beta
Classifier: Intended Audience :: Developers
Classifier: License :: OSI Approved :: BSD License
Classifier: Natural Language :: English
Classifier: Programming Language :: Python :: 2
Classifier: Programming Language :: Python :: 2.6
Classifier: Programming Language :: Python :: 2.7
Classifier: Programming Language :: Python :: 3
Classifier: Programming Language :: Python :: 3.3
Classifier: Programming Language :: Python :: 3.4
Requires-Dist: cffi (==1.1.0)
Requires-Dist: couchbase (==2.0)
Requires-Dist: python-dateutil (==2.1)
Requires-Dist: jsonpickle (==0.9.2)
